dirtyflags/__init__.py
dirtyflags/dirtyflags.py
dirtyflags-1.5.0.dist-info/licenses/LICENSE
dirtyflags-1.5.0.dist-info/METADATA
dirtyflags-1.5.0.dist-info/WHEEL
dirtyflags-1.5.0.dist-info/top_level.txt
dirtyflags-1.5.0.dist-info/RECORD
