Metadata-Version: 2.4
Name: dirtyflags
Version: 1.5.0
Summary: dirtyflags is a simple Python decorator that tracks when and which instance attributes have changed.
Author-email: James J Johnson <james.x.johnson@gmail.com>
Project-URL: repository, https://github.com/jamesxcode/dirtyflags
License-File: LICENSE
Dynamic: license-file
